delphi4py/__init__.py
delphi4py/defaults.py
delphi4py/delphi4py.py
delphi4py/readFiles/readFiles.cpython-310-x86_64-linux-gnu.so
delphi4py/readFiles/readFiles.cpython-311-x86_64-linux-gnu.so
delphi4py/readFiles/readFiles.cpython-312-x86_64-linux-gnu.so
delphi4py/readFiles/readFiles.cpython-313-x86_64-linux-gnu.so
delphi4py/readFiles/readFiles.cpython-36m-x86_64-linux-gnu.so
delphi4py/readFiles/readFiles.cpython-37m-x86_64-linux-gnu.so
delphi4py/readFiles/readFiles.cpython-38-x86_64-linux-gnu.so
delphi4py/readFiles/readFiles.cpython-39-x86_64-linux-gnu.so
delphi4py/rundelphi/rundelphi.cpython-310-x86_64-linux-gnu.so
delphi4py/rundelphi/rundelphi.cpython-311-x86_64-linux-gnu.so
delphi4py/rundelphi/rundelphi.cpython-312-x86_64-linux-gnu.so
delphi4py/rundelphi/rundelphi.cpython-313-x86_64-linux-gnu.so
delphi4py/rundelphi/rundelphi.cpython-36m-x86_64-linux-gnu.so
delphi4py/rundelphi/rundelphi.cpython-37m-x86_64-linux-gnu.so
delphi4py/rundelphi/rundelphi.cpython-38-x86_64-linux-gnu.so
delphi4py/rundelphi/rundelphi.cpython-39-x86_64-linux-gnu.so
delphi4py-1.4.0.dist-info/LICENSE
delphi4py-1.4.0.dist-info/METADATA
delphi4py-1.4.0.dist-info/WHEEL
delphi4py-1.4.0.dist-info/top_level.txt
delphi4py-1.4.0.dist-info/RECORD
