Metadata-Version: 2.2
Name: delphi4py
Version: 1.4.0
Summary: A python wrapper for the Poisson-Boltzmann Equation solver DelPhi
Home-page: https://github.com/pedrishi/delphi4py
Author: Pedro B.P.S. Reis
Author-email: preis@fc.ul.pt
License-File: LICENSE
Dynamic: author
Dynamic: author-email
Dynamic: description
Dynamic: description-content-type
Dynamic: home-page
Dynamic: summary
